{
    "category": "NobleHouses", 
    "images": [
        {
            "url": "http://awoiaf.westeros.org/images/thumb/7/77/Harroway.png/250px-Harroway.png", 
            "caption": ""
        }
    ], 
    "name": "House Harroway", 
    "summary": "<p><b>House Harroway of Harrenhal</b> is an extinct noble house from <a href=\"http://awoiaf.westeros.org/index.php/Harrenhal\" title=\"Harrenhal\">Harrenhal</a> in <a href=\"http://awoiaf.westeros.org/index.php/The_Riverlands\" title=\"The Riverlands\" class=\"mw-redirect\">the Riverlands</a>. According to semi-canon sources they blazoned their arms with per bend sinister orange and black rayonne, a castle countercharged.<sup id=\"cite_ref-Citadel_0-0\" class=\"reference\"><a href=\"http://awoiaf.westeros.org/index.php/House Harroway#cite_note-Citadel-0\">[1]</a></sup> <a href=\"http://awoiaf.westeros.org/index.php/Lord_Harroway%27s_Town\" title=\"Lord Harroway's Town\">Lord Harroway's Town</a> is named after a former lord of the house.<sup id=\"cite_ref-Rasos47.7B.7B.7B3.7D.7D.7D_1-0\" class=\"reference\"><a href=\"http://awoiaf.westeros.org/index.php/House Harroway#cite_note-Rasos47.7B.7B.7B3.7D.7D.7D-1\">[2]</a></sup>"
}