{
    "category": "NobleHouses", 
    "images": [
        {
            "url": "http://awoiaf.westeros.org/images/thumb/2/27/Saltcliffe.png/250px-Saltcliffe.png", 
            "caption": ""
        }
    ], 
    "name": "House Saltcliffe", 
    "summary": "<p><b>House Saltcliffe of Saltcliffe</b> is one of the <a href=\"http://awoiaf.westeros.org/index.php/Ironborn\" title=\"Ironborn\">ironborn</a> noble houses on the island of <a href=\"http://awoiaf.westeros.org/index.php/Saltcliffe\" title=\"Saltcliffe\">Saltcliffe</a> in the <a href=\"http://awoiaf.westeros.org/index.php/Iron_Islands\" title=\"Iron Islands\">Iron Islands</a>."
}