{
    "category": "NobleHouses", 
    "images": [
        {
            "url": "http://awoiaf.westeros.org/images/thumb/d/d1/Roote.png/250px-Roote.png", 
            "caption": ""
        }
    ], 
    "name": "House Roote", 
    "summary": "<p><b>House Roote of Lord Harroway's Town</b> is a noble house from <a href=\"http://awoiaf.westeros.org/index.php/Lord_Harroway%27s_Town\" title=\"Lord Harroway's Town\">Harroway</a> in the <a href=\"http://awoiaf.westeros.org/index.php/Riverlands\" title=\"Riverlands\">Riverlands</a>. According to semi-canon sources, they blazon their arms with a two-headed horse, brown, on a field of wavy green and green.<sup id=\"cite_ref-0\" class=\"reference\"><a href=\"http://awoiaf.westeros.org/index.php/House Roote#cite_note-0\">[1]</a></sup>"
}