{
    "category": "NobleHouses", 
    "images": [
        {
            "url": "http://awoiaf.westeros.org/images/thumb/5/52/Dunn.png/250px-Dunn.png", 
            "caption": ""
        }
    ], 
    "name": "House Dunn", 
    "summary": "<p><b>House Dunn</b> is a noble house from the <a href=\"http://awoiaf.westeros.org/index.php/Reach\" title=\"Reach\" class=\"mw-redirect\">Reach</a>. According to semi-canon sources House Dunn blazons its shields with per pale black and pink, a countercharged two-headed pelican.<sup id=\"cite_ref-0\" class=\"reference\"><a href=\"http://awoiaf.westeros.org/index.php/House Dunn#cite_note-0\">[1]</a></sup>"
}