{
    "category": "Castles", 
    "images": [
        {
            "url": "http://awoiaf.westeros.org/images/thumb/8/89/The_Reach.png/400px-The_Reach.png", 
            "caption": "The Reach and the location of Grassfield Keep"
        }
    ], 
    "name": "Grassfield Keep", 
    "summary": "<p><b>Grassfield Keep</b> is the castle of <a href=\"http://awoiaf.westeros.org/index.php/House_Meadows\" title=\"House Meadows\">House Meadows</a> in or near the town of <a href=\"http://awoiaf.westeros.org/index.php/Grassy_Vale\" title=\"Grassy Vale\">Grassy Vale</a> in <a href=\"http://awoiaf.westeros.org/index.php/The_Reach\" title=\"The Reach\">the Reach</a>.<sup id=\"cite_ref-0\" class=\"reference\"><a href=\"http://awoiaf.westeros.org/index.php/Grassfield Keep#cite_note-0\">[1]</a></sup><sup id=\"cite_ref-Radwdappendix.7B.7B.7B3.7D.7D.7D_1-0\" class=\"reference\"><a href=\"http://awoiaf.westeros.org/index.php/Grassfield Keep#cite_note-Radwdappendix.7B.7B.7B3.7D.7D.7D-1\">[2]</a></sup>"
}