{
    "category": "NobleHouses", 
    "images": [
        {
            "url": "http://awoiaf.westeros.org/images/thumb/5/5c/Coats_of_arms_of_None.png/200px-Coats_of_arms_of_None.png", 
            "caption": ""
        }
    ], 
    "name": "House Ironmaker", 
    "summary": "<p><b>House Ironmaker</b> is a minor noble house from the <a href=\"http://awoiaf.westeros.org/index.php/Iron_Islands\" title=\"Iron Islands\">Iron Islands</a>.<sup id=\"cite_ref-0\" class=\"reference\"><a href=\"http://awoiaf.westeros.org/index.php/House Ironmaker#cite_note-0\">[1]</a></sup> Neither its arms nor its words are known."
}