{
    "category": "NobleHouses", 
    "images": [
        {
            "url": "http://awoiaf.westeros.org/images/thumb/a/a6/Sunglass.png/250px-Sunglass.png", 
            "caption": ""
        }
    ], 
    "name": "House Sunglass", 
    "summary": "<p><b>House Sunglass of Sweetport Sound</b> is a noble house sworn to <a href=\"http://awoiaf.westeros.org/index.php/Dragonstone\" title=\"Dragonstone\">Dragonstone</a>, with an old and deep faith in <a href=\"http://awoiaf.westeros.org/index.php/Faith_of_the_Seven\" title=\"Faith of the Seven\">the Seven</a>. The exact location of <a href=\"http://awoiaf.westeros.org/index.php/Sweetport_Sound\" title=\"Sweetport Sound\">Sweetport Sound</a> in the <a href=\"http://awoiaf.westeros.org/index.php/Crownlands\" title=\"Crownlands\">Crownlands</a> has not been stated."
}