{
    "category": "Other", 
    "images": [
        {
            "url": "http://awoiaf.westeros.org/images/thumb/d/d0/The_Riverlands.png/400px-The_Riverlands.png", 
            "caption": "The Riverlands and the location of Lord Harroway\\'s Town"
        }
    ], 
    "name": "Lord Harroway's Town", 
    "summary": "<p><b>Lord Harroway's Town</b>, called <b>Harroway</b> for short,<sup id=\"cite_ref-0\" class=\"reference\"><a href=\"http://awoiaf.westeros.org/index.php/Lord Harroway's Town#cite_note-0\">[1]</a></sup> is a town in the <a href=\"http://awoiaf.westeros.org/index.php/Riverlands\" title=\"Riverlands\">Riverlands</a> that sits along the <a href=\"http://awoiaf.westeros.org/index.php/Trident\" title=\"Trident\">Trident</a>. It is the seat of <a href=\"http://awoiaf.westeros.org/index.php/House_Roote\" title=\"House Roote\">House Roote</a>. It has a seven-sided <a href=\"http://awoiaf.westeros.org/index.php/Sept\" title=\"Sept\">sept</a>, a two-story inn and a stone roundtower,<sup id=\"cite_ref-Rasos47.7B.7B.7B3.7D.7D.7D_1-0\" class=\"reference\"><a href=\"http://awoiaf.westeros.org/index.php/Lord Harroway's Town#cite_note-Rasos47.7B.7B.7B3.7D.7D.7D-1\">[2]</a></sup> <a href=\"http://awoiaf.westeros.org/index.php/Harroway_Tower\" title=\"Harroway Tower\">Harroway Tower</a>.<sup id=\"cite_ref-2\" class=\"reference\"><a href=\"http://awoiaf.westeros.org/index.php/Lord Harroway's Town#cite_note-2\">[3]</a></sup> It is named after an extinct noble house, <a href=\"http://awoiaf.westeros.org/index.php/House_Harroway\" title=\"House Harroway\">House Harroway</a>."
}